pdfgridcat/__init__.py
pdfgridcat/cli.py
pdfgridcat-1.0.0.dist-info/METADATA
pdfgridcat-1.0.0.dist-info/WHEEL
pdfgridcat-1.0.0.dist-info/entry_points.txt
pdfgridcat-1.0.0.dist-info/top_level.txt
pdfgridcat-1.0.0.dist-info/RECORD
