Metadata-Version: 2.4
Name: pdfgridcat
Version: 1.0.0
Summary: Arrange multiple PDF pages into a grid without scaling or margins
Author: Katsutoshi Seki
License: MIT
Project-URL: Homepage, https://github.com/sekika/pdfgridcat
Keywords: pdf,pypdf,concat,grid,tile
Classifier: Development Status :: 5 - Production/Stable
Classifier: Intended Audience :: Developers
Classifier: Topic :: Software Development :: Libraries
Classifier: Topic :: Utilities
Classifier: License :: OSI Approved :: MIT License
Classifier: Programming Language :: Python :: 3
Classifier: Programming Language :: Python :: 3.8
Classifier: Programming Language :: Python :: 3.9
Classifier: Programming Language :: Python :: 3.10
Classifier: Programming Language :: Python :: 3.11
Classifier: Operating System :: OS Independent
Requires-Python: >=3.8
Requires-Dist: pypdf>=4.0.0
